uctp/__init__.py
uctp/additional.py
uctp/cli.py
uctp/peer.py
uctp/protocol.py
uctp-1.0.0a6.dev1.data/scripts/uctp
uctp-1.0.0a6.dev1.dist-info/LICENSE.md
uctp-1.0.0a6.dev1.dist-info/METADATA
uctp-1.0.0a6.dev1.dist-info/WHEEL
uctp-1.0.0a6.dev1.dist-info/top_level.txt
uctp-1.0.0a6.dev1.dist-info/RECORD
